django_shorts.py
django_shorts-1.1.dist-info/LICENSE.txt
django_shorts-1.1.dist-info/METADATA
django_shorts-1.1.dist-info/WHEEL
django_shorts-1.1.dist-info/entry_points.txt
django_shorts-1.1.dist-info/top_level.txt
django_shorts-1.1.dist-info/RECORD
