Metadata-Version: 2.1
Name: django-shorts
Version: 1.1
Summary: You spend way too much time typing 'python manage.py'
Home-page: https://github.com/mhadiahmed/django-shorts.git
Author: Mhadi Ahmed
Author-email: mhadiahmed63@gmail.com
License: UNKNOWN
Platform: UNKNOWN
Classifier: Development Status :: 5 - Production/Stable
Classifier: Intended Audience :: Developers
Classifier: Natural Language :: English
Classifier: License :: OSI Approved :: MIT License
Classifier: Programming Language :: Python
Classifier: Programming Language :: Python :: 3.8
Classifier: Programming Language :: Python :: 3.8
